gemini_cli_sdk/__init__.py
gemini_cli_sdk/client.py
gemini_cli_sdk/enums.py
gemini_cli_sdk/errors.py
gemini_cli_sdk/mcp.py
gemini_cli_sdk/models.py
gemini_cli_sdk/options.py
gemini_cli_sdk/py.typed
gemini_cli_sdk/settings.py
gemini_cli_sdk/spec.py
gemini_cli_sdk_py-0.1.1.dist-info/METADATA
gemini_cli_sdk_py-0.1.1.dist-info/WHEEL
gemini_cli_sdk_py-0.1.1.dist-info/licenses/LICENSE
gemini_cli_sdk_py-0.1.1.dist-info/RECORD
