Metadata-Version: 2.4
Name: gemini-cli-sdk-py
Version: 0.1.1
Summary: Fully-typed Python SDK that wraps the Gemini CLI (google-gemini/gemini-cli).
Project-URL: Homepage, https://github.com/thehumanworks/gemini-cli-sdk-py
Project-URL: Source, https://github.com/thehumanworks/gemini-cli-sdk-py
Author-email: Tomas Roda <dev@tomasroda.com>
License: Apache-2.0
License-File: LICENSE
Keywords: cli,gemini,google,mcp,sdk
Classifier: Development Status :: 4 - Beta
Classifier: Intended Audience :: Developers
Classifier: License :: OSI Approved :: Apache Software License
Classifier: Programming Language :: Python :: 3
Classifier: Programming Language :: Python :: 3.10
Classifier: Programming Language :: Python :: 3.11
Classifier: Programming Language :: Python :: 3.12
Classifier: Programming Language :: Python :: 3.13
Classifier: Typing :: Typed
Requires-Python: >=3.10
Requires-Dist: pydantic<3,>=2.6.0
Requires-Dist: typing-extensions>=4.9.0; python_version < '3.11'
Provides-Extra: dev
Requires-Dist: mypy>=1.10.0; extra == 'dev'
Requires-Dist: pytest-cov>=5.0.0; extra == 'dev'
Requires-Dist: pytest>=8.0.0; extra == 'dev'
Requires-Dist: ruff>=0.6.0; extra == 'dev'
